image_to_form_app/__init__.py
image_to_form_app/gui.py
image_to_form_app/main.py
image_to_form_app-0.2.dist-info/METADATA
image_to_form_app-0.2.dist-info/WHEEL
image_to_form_app-0.2.dist-info/entry_points.txt
image_to_form_app-0.2.dist-info/top_level.txt
image_to_form_app-0.2.dist-info/RECORD
